openbrokerapi/__init__.py
openbrokerapi/api.py
openbrokerapi/auth.py
openbrokerapi/catalog.py
openbrokerapi/constants.py
openbrokerapi/errors.py
openbrokerapi/helper.py
openbrokerapi/log_util.py
openbrokerapi/request_filter.py
openbrokerapi/response.py
openbrokerapi/router.py
openbrokerapi/service_broker.py
openbrokerapi/settings.py
openbrokerapi-4.7.3.dist-info/METADATA
openbrokerapi-4.7.3.dist-info/WHEEL
openbrokerapi-4.7.3.dist-info/licenses/LICENSE
openbrokerapi-4.7.3.dist-info/RECORD
