Metadata-Version: 2.4
Name: openbrokerapi
Version: 4.7.3
Summary: A python package for the V2 CF Service Broker API and Open Broker API (version 2.13+)
Project-URL: Homepage, https://openbrokerapi.readthedocs.io/
Project-URL: Documentation, https://openbrokerapi.readthedocs.io/
Project-URL: Repository, https://github.com/eruvanos/openbrokerapi
Project-URL: Issue Tracker, https://github.com/eruvanos/openbrokerapi/issues
Project-URL: Changelog, https://github.com/eruvanos/openbrokerapi/blob/main/CHANGELOG.rst
Author-email: Maic Siemering <maic@siemering.tech>
License: MIT
License-File: LICENSE
Keywords: cfbrokerapi,cloudfoundry,flask,k8s,kubernetes,openbrokerapi,openservicebrokerapi,servicebroker
Classifier: Development Status :: 5 - Production/Stable
Classifier: Framework :: Flask
Classifier: Intended Audience :: Developers
Classifier: License :: OSI Approved :: MIT License
Classifier: Operating System :: OS Independent
Classifier: Programming Language :: Python :: 3 :: Only
Classifier: Programming Language :: Python :: 3.8
Classifier: Programming Language :: Python :: 3.9
Classifier: Programming Language :: Python :: 3.10
Classifier: Programming Language :: Python :: 3.11
Classifier: Programming Language :: Python :: 3.12
Classifier: Programming Language :: Python :: 3.13
Requires-Python: >=3.8
Requires-Dist: flask<4.0.0,>=3.0.3
Provides-Extra: gevent
Requires-Dist: gevent>=22.10.2; extra == 'gevent'
Provides-Extra: gunicorn
Requires-Dist: gunicorn>=20.1; extra == 'gunicorn'
